statedict2pytree/__init__.py
statedict2pytree/converter.py
statedict2pytree-1.0.1.dist-info/METADATA
statedict2pytree-1.0.1.dist-info/WHEEL
statedict2pytree-1.0.1.dist-info/RECORD
