Metadata-Version: 2.3
Name: statedict2pytree
Version: 1.0.1
Summary: Converts torch models into PyTrees for Equinox
Author-email: "Artur A. Galstyan" <mail@arturgalstyan.dev>
Requires-Python: >=3.11
Requires-Dist: beartype
Requires-Dist: equinox
Requires-Dist: jax
Requires-Dist: jaxlib
Requires-Dist: jaxtyping
Requires-Dist: pydantic
Requires-Dist: tqdm
Provides-Extra: dev
Requires-Dist: mkdocs; extra == 'dev'
Requires-Dist: pre-commit; extra == 'dev'
Requires-Dist: pytest; extra == 'dev'
Requires-Dist: torch; extra == 'dev'
Provides-Extra: examples
Requires-Dist: jaxonmodels; extra == 'examples'
